flask_authorization/__init__.py
flask_authorization/decorators.py
flask_authorization/main.py
flask_authorization-1.6.dist-info/LICENSE
flask_authorization-1.6.dist-info/WHEEL
flask_authorization-1.6.dist-info/METADATA
flask_authorization-1.6.dist-info/RECORD
