Metadata-Version: 2.1
Name: flask-authorization
Version: 1.6
Summary: Simple user authorization to use alongside with Flask-Login
Home-page: https://github.com/mkrd/flask-authorization
License: MIT
Author: Marcel Kröker
Author-email: kroeker.marcel@gmail.com
Requires-Python: >=3.8,<4.0
Classifier: License :: OSI Approved :: MIT License
Classifier: Programming Language :: Python :: 3
Classifier: Programming Language :: Python :: 3.10
Classifier: Programming Language :: Python :: 3.8
Classifier: Programming Language :: Python :: 3.9
Requires-Dist: Flask (>=2.0.1,<3.0.0)
Requires-Dist: flask-login (>=0.5.0,<1.0.0)
Project-URL: Repository, https://github.com/mkrd/flask-authorization
